whippy/__init__.py
whippy/settings.py
whippy/whippy.py
whippy-0.8.2.dist-info/METADATA
whippy-0.8.2.dist-info/RECORD
whippy-0.8.2.dist-info/WHEEL
whippy-0.8.2.dist-info/top_level.txt
