Metadata-Version: 2.1
Name: whippy
Version: 0.8.2
Summary: Rapidly scaffold WordPress sites on Linux NGINX servers from the command line. Unrelated to the wppy project, although both fill the same hole.
Home-page: https://github.com/erikcaineolson/whippy
Author: Erik C. Olson
Author-email: erikcaineolson@gmail.com
License: MIT
Platform: UNKNOWN
Classifier: Programming Language :: Python :: 3
Classifier: License :: OSI Approved :: MIT License
Classifier: Operating System :: OS Independent
